newfile/__init__.py
newfile/__main__.py
newfile-0.1.1.dist-info/entry_points.txt
newfile-0.1.1.dist-info/WHEEL
newfile-0.1.1.dist-info/METADATA
newfile-0.1.1.dist-info/LICENSE
newfile-0.1.1.dist-info/RECORD
