Metadata-Version: 2.1
Name: newfile
Version: 0.1.1
Summary: create files from preset template cli app
License: MIT
Author-email: teeaz <teeaz@github.com>
Requires-Python: >=3.9
Requires-Dist: click>=8.0.3
Requires-Dist: lazyaml>=6.0.4
Requires-Dist: rich>=11.2.0
Project-URL: homepage, https://github.com/teeaz/newfile
